Metadata-Version: 2.1
Name: MathOpo
Version: 0.0.1
Summary: Esto es una prueba de paquete
Home-page: https://github.com/Shushant94/MathOpo.git
Author: Shushant Mohan Kumari
License: MIT
License-File: LICENSE
